gluepyter/__init__.py
gluepyter/_version.py
gluepyter/glue_session.py
gluepyter/glue_utils.py
gluepyter/glue_ydoc.py
gluepyter/handlers.py
gluepyter/tests/__init__.py
gluepyter/tests/conftest.py
gluepyter/tests/test_glue_session.py
gluepyter/tests/test_handlers.py
gluepyter/tests/test_ydoc.py
gluepyter-0.1.0.data/data/etc/jupyter/jupyter_notebook_config.d/glue_lab.json
gluepyter-0.1.0.data/data/etc/jupyter/jupyter_server_config.d/glue_lab.json
gluepyter-0.1.0.data/data/share/jupyter/labextensions/gluepyter/package.json
gluepyter-0.1.0.data/data/share/jupyter/labextensions/gluepyter/static/185.6c511cfc049030bac651.js
gluepyter-0.1.0.data/data/share/jupyter/labextensions/gluepyter/static/398.2a55c1fb58b1ac3330ec.js
gluepyter-0.1.0.data/data/share/jupyter/labextensions/gluepyter/static/797.503d396291a5b2e423ba.js
gluepyter-0.1.0.data/data/share/jupyter/labextensions/gluepyter/static/929.fee4f63edd755a5479ad.js
gluepyter-0.1.0.data/data/share/jupyter/labextensions/gluepyter/static/929.fee4f63edd755a5479ad.js.LICENSE.txt
gluepyter-0.1.0.data/data/share/jupyter/labextensions/gluepyter/static/remoteEntry.80898d98902552f99aed.js
gluepyter-0.1.0.data/data/share/jupyter/labextensions/gluepyter/static/style.js
gluepyter-0.1.0.data/data/share/jupyter/labextensions/gluepyter/static/third-party-licenses.json
gluepyter-0.1.0.data/data/share/jupyter/labextensions/gluepyter/install.json
gluepyter-0.1.0.dist-info/METADATA
gluepyter-0.1.0.dist-info/WHEEL
gluepyter-0.1.0.dist-info/entry_points.txt
gluepyter-0.1.0.dist-info/licenses/LICENSE
gluepyter-0.1.0.dist-info/RECORD
